data_factory_testing_framework/__init__.py
data_factory_testing_framework/_enum_meta.py
data_factory_testing_framework/_test_framework.py
data_factory_testing_framework/py.typed
data_factory_testing_framework/_deserializers/__init__.py
data_factory_testing_framework/_deserializers/_deserializer_base.py
data_factory_testing_framework/_deserializers/_deserializer_data_factory.py
data_factory_testing_framework/_deserializers/_deserializer_fabric.py
data_factory_testing_framework/_deserializers/shared/__init__.py
data_factory_testing_framework/_deserializers/shared/_activity_deserializer.py
data_factory_testing_framework/_deserializers/shared/_data_factory_element_replacer.py
data_factory_testing_framework/_expression_runtime/expression_runtime.py
data_factory_testing_framework/_expression_runtime/functions_repository.py
data_factory_testing_framework/_expression_runtime/data_factory_expression/__init__.py
data_factory_testing_framework/_expression_runtime/data_factory_expression/data_factory_to_expression_transformer.py
data_factory_testing_framework/_expression_runtime/data_factory_expression/exceptions.py
data_factory_testing_framework/_expression_runtime/data_factory_expression/expression_transformer.py
data_factory_testing_framework/_pythonnet/Evaluator.csproj
data_factory_testing_framework/_pythonnet/__init__.py
data_factory_testing_framework/_pythonnet/data_factory_testing_framework_expressions_evaluator.py
data_factory_testing_framework/_pythonnet/bin/DotLiquid.dll
data_factory_testing_framework/_pythonnet/bin/Evaluator.deps.json
data_factory_testing_framework/_pythonnet/bin/Evaluator.dll
data_factory_testing_framework/_pythonnet/bin/Evaluator.pdb
data_factory_testing_framework/_pythonnet/bin/Microsoft.AspNetCore.Antiforgery.dll
data_factory_testing_framework/_pythonnet/bin/Microsoft.AspNetCore.Authentication.Abstractions.dll
data_factory_testing_framework/_pythonnet/bin/Microsoft.AspNetCore.Authentication.Core.dll
data_factory_testing_framework-1.4.0.dist-info/licenses/LICENSE
data_factory_testing_framework-1.4.0.dist-info/METADATA
data_factory_testing_framework-1.4.0.dist-info/WHEEL
data_factory_testing_framework-1.4.0.dist-info/top_level.txt
data_factory_testing_framework-1.4.0.dist-info/RECORD
