Metadata-Version: 2.4
Name: data-factory-testing-framework
Version: 1.4.0
Summary: A stand-alone test framework that allows to write unit tests for Data Factory pipelines on Microsoft Fabric, Azure Data Factory and Azure Synapse Analytics.
Author-email: Data Factory Testing Framework <dftf@microsoft.com>
License-Expression: MIT
Project-URL: Homepage, https://github.com/microsoft/data-factory-testing-framework
Project-URL: Documentation, https://github.com/microsoft/data-factory-testing-framework/blob/main/README.md
Project-URL: Issues, https://github.com/microsoft/data-factory-testing-framework/issues
Project-URL: Source, https://github.com/microsoft/data-factory-testing-framework.git
Keywords: fabric,datafactory,synapse analytics,unit-testing,functional-testing,azure
Classifier: Programming Language :: Python :: 3.9
Classifier: Programming Language :: Python :: 3.10
Classifier: Programming Language :: Python :: 3.11
Classifier: Programming Language :: Python :: 3.12
Classifier: Operating System :: OS Independent
Requires-Python: <3.14,>=3.9
License-File: LICENSE
Requires-Dist: lark<2.0.0,>=1.1.8
Requires-Dist: pythonnet<4.0.0,>=3.0.3
Dynamic: license-file
